id_validation/__init__.py
id_validation/registry.py
id_validation/validate.py
id_validation/validate_belgium.py
id_validation/validate_botswana.py
id_validation/validate_finland.py
id_validation/validate_france.py
id_validation/validate_italy.py
id_validation/validate_nigeria.py
id_validation/validate_norway.py
id_validation/validate_southafrica.py
id_validation/validate_spain.py
id_validation/validate_sweden.py
id_validation/validate_zimbabwe.py
id_validation/validators/ar_cuit_cuil.py
id_validation/validators/base.py
id_validation/validators/bg_egn.py
id_validation/validators/br_cpf.py
id_validation/validators/ca_sin.py
id_validation/validators/cl_rut.py
id_validation/validators/co_nit.py
id_validation/validators/cz_rodne_cislo.py
id_validation/validators/dk_cpr.py
id_validation/validators/ec_cedula.py
id_validation/validators/ee_isikukood.py
id_validation/validators/hr_oib.py
id_validation/validators/lt_asmenskodas.py
id_validation/validators/lv_personas_kods.py
id_validation/validators/mx_curp.py
id_validation/validators/nl_bsn.py
id_validation/validators/pl_pesel.py
id_validation/validators/pt_nif.py
id_validation/validators/ro_cnp.py
id_validation/validators/si_emso.py
id_validation/validators/sk_rodne_cislo.py
id_validation/validators/tr_tckn.py
id_validation-0.6.1.dist-info/licenses/LICENSE
id_validation-0.6.1.dist-info/METADATA
id_validation-0.6.1.dist-info/WHEEL
id_validation-0.6.1.dist-info/top_level.txt
id_validation-0.6.1.dist-info/RECORD
