Metadata-Version: 2.4
Name: id-validation
Version: 0.6.1
Summary: A library to validate and extract information from national id numbers
Author-email: Adi Eyal <adi@clearforest.io>
License: Copyright 2022 Adi Eyal
Project-URL: Homepage, https://github.com/adieyal/id_validation/
Keywords: id numbers,validation
Classifier: License :: OSI Approved :: MIT License
Classifier: Programming Language :: Python
Classifier: Programming Language :: Python :: 3
Requires-Python: >=3.9
License-File: LICENSE
Provides-Extra: dev
Requires-Dist: pytest; extra == "dev"
Requires-Dist: build; extra == "dev"
Requires-Dist: twine; extra == "dev"
Dynamic: license-file
